py2exelite/__init__.py
py2exelite/__main__.py
py2exelite/builder.py
py2exelite-1.0.0.dist-info/licenses/LICENSE
py2exelite-1.0.0.dist-info/METADATA
py2exelite-1.0.0.dist-info/WHEEL
py2exelite-1.0.0.dist-info/entry_points.txt
py2exelite-1.0.0.dist-info/top_level.txt
py2exelite-1.0.0.dist-info/RECORD
