Metadata-Version: 2.4
Name: Py2ExeLite
Version: 1.0.0
Summary: Lightweight tool to convert Python scripts into .exe files with style
Home-page: https://github.com/PozStudio/Py2ExeLite
Author: Poyraz (PozStudio)
Author-email: pozstudio.dev@gmail.com
Project-URL: Bug Tracker, https://github.com/PozStudio/Py2ExeLite/issues
Classifier: Development Status :: 5 - Production/Stable
Classifier: License :: OSI Approved :: MIT License
Classifier: Programming Language :: Python :: 3
Classifier: Operating System :: Microsoft :: Windows
Classifier: Topic :: Software Development :: Build Tools
Requires-Python: >=3.6
License-File: LICENSE
Dynamic: author
Dynamic: author-email
Dynamic: classifier
Dynamic: description
Dynamic: description-content-type
Dynamic: home-page
Dynamic: license-file
Dynamic: project-url
Dynamic: requires-python
Dynamic: summary
